CONTRIBUTORS.txt
HISTORY.txt
README.txt
bootstrap.py
buildout.cfg
setup.py
collective/__init__.py
collective.testswarm.egg-info/PKG-INFO
collective.testswarm.egg-info/SOURCES.txt
collective.testswarm.egg-info/dependency_links.txt
collective.testswarm.egg-info/entry_points.txt
collective.testswarm.egg-info/namespace_packages.txt
collective.testswarm.egg-info/not-zip-safe
collective.testswarm.egg-info/requires.txt
collective.testswarm.egg-info/top_level.txt
collective/testswarm/__init__.py
collective/testswarm/configure.zcml
collective/testswarm/example-qunit-suite.pt
collective/testswarm/interfaces.py
collective/testswarm/layers.py
collective/testswarm/tests.py
collective/testswarm/utils.py
collective/testswarm/version.txt
collective/testswarm/javascript/example-qunit-test.js
collective/testswarm/profiles/test/browserlayer.xml
collective/testswarm/profiles/test/cssregistry.xml
collective/testswarm/profiles/test/jsregistry.xml
collective/testswarm/profiles/test/metadata.xml