Metadata-Version: 1.0
Name: collective.testswarm
Version: 0.3
Summary: Plone TestSwarm integration package
Home-page: http://cillian.wordpress.com
Author: Cillian de Roiste
Author-email: cillian.deroiste@gmail.com
License: AGPLv3+
Keywords: Plone TestSwarm JavaScript Continuous-Integration
Platform: UNKNOWN
Classifier: Framework :: Plone
Classifier: Programming Language :: Python
Classifier: Programming Language :: JavaScript
Classifier: Topic :: Software Development :: Testing
Classifier: Topic :: Software Development :: Libraries :: Python Modules
Classifier: License :: OSI Approved :: GNU Affero General Public License v3
